tests/__init__.py
tests/test_language.py
tree_sitter_surrealql/__init__.py
tree_sitter_surrealql/__init__.pyi
tree_sitter_surrealql/_binding.abi3.so
tree_sitter_surrealql/binding.c
tree_sitter_surrealql/py.typed
tree_sitter_surrealql/queries/folds.scm
tree_sitter_surrealql/queries/highlights.scm
tree_sitter_surrealql/queries/indents.scm
tree_sitter_surrealql-0.2.0.dist-info/LICENSE
tree_sitter_surrealql-0.2.0.dist-info/METADATA
tree_sitter_surrealql-0.2.0.dist-info/WHEEL
tree_sitter_surrealql-0.2.0.dist-info/top_level.txt
tree_sitter_surrealql-0.2.0.dist-info/RECORD
