Metadata-Version: 2.1
Name: tree-sitter-surrealql
Version: 0.2.0
Summary: SurrealQL grammar for tree-sitter
Author-email: Cellan Hall <hallcellan@gmail.com>
License: MIT
Project-URL: Homepage, https://github.com/ce11an/tree-sitter-surrealql
Keywords: incremental,parsing,tree-sitter,surrealql
Classifier: Intended Audience :: Developers
Classifier: License :: OSI Approved :: MIT License
Classifier: Topic :: Software Development :: Compilers
Classifier: Topic :: Text Processing :: Linguistic
Classifier: Typing :: Typed
Requires-Python: >=3.8
License-File: LICENSE
Provides-Extra: core
Requires-Dist: tree-sitter~=0.21; extra == "core"
